mpyl/__init__.py
mpyl/project.py
mpyl/stage.py
mpyl/target.py
mpyl/projects/__init__.py
mpyl/projects/find.py
mpyl/repo/__init__.py
mpyl/stages/__init__.py
mpyl/stages/discovery.py
mpyl/steps/__init__.py
mpyl/steps/models.py
mpyl/steps/step.py
mpyl/steps/steps.py
mpyl/steps/build/__init__.py
mpyl/steps/build/docker_after_build.py
mpyl/steps/build/dockerbuild.py
mpyl/steps/build/echo.py
mpyl/steps/deploy/__init__.py
mpyl/steps/deploy/echo.py
mpyl/steps/deploy/kubernetes.py
mpyl/steps/deploy/k8s/__init__.py
mpyl/steps/deploy/k8s/helm.py
mpyl/steps/deploy/k8s/rancher.py
mpyl/steps/deploy/k8s/resources.py
mpyl/steps/deploy/k8s/service.py
mpyl-2.dist-info/LICENSE
mpyl-2.dist-info/METADATA
mpyl-2.dist-info/WHEEL
mpyl-2.dist-info/top_level.txt
mpyl-2.dist-info/RECORD
