Metadata-Version: 2.1
Name: mpyl
Version: 2
Summary: Modular Pipeline Library
License-File: LICENSE
Requires-Dist: jsonschema (==4.17.0)
Requires-Dist: mypy (==0.991)
Requires-Dist: gitpython (==3.1.29)
Requires-Dist: docker (==6.0.1)
Requires-Dist: ruamel.yaml (==0.17.21)
Requires-Dist: kubernetes (==25.3.0)
